aiosysbus/__init__.py
aiosysbus/aiosysbus.py
aiosysbus/auth.py
aiosysbus/exceptions.py
aiosysbus/py.typed
aiosysbus/api/__init__.py
aiosysbus/api/call.py
aiosysbus/api/device.py
aiosysbus/api/diagnostic.py
aiosysbus/api/dnsdhcp.py
aiosysbus/api/nemo.py
aiosysbus/api/network.py
aiosysbus/api/nmc.py
aiosysbus/api/powermgmt.py
aiosysbus/api/schedule.py
aiosysbus/api/services.py
aiosysbus/api/sgcomci.py
aiosysbus/api/storage.py
aiosysbus/api/system.py
aiosysbus/api/user.py
aiosysbus-1.2.4.dist-info/licenses/LICENSE
aiosysbus-1.2.4.dist-info/METADATA
aiosysbus-1.2.4.dist-info/WHEEL
aiosysbus-1.2.4.dist-info/top_level.txt
aiosysbus-1.2.4.dist-info/RECORD
