Metadata-Version: 2.4
Name: aiosysbus
Version: 1.2.4
Summary: Provides asynchronous authentication and access to Livebox
Author-email: Cyr-ius <cyr-ius@ipocus.net>
License: GPL-3
Project-URL: Homepage, https://github.com/cyr-ius/aiosysbus
Keywords: livebox,async
Classifier: Programming Language :: Python
Classifier: Development Status :: 5 - Production/Stable
Classifier: License :: OSI Approved :: GNU General Public License v3 or later (GPLv3+)
Classifier: Programming Language :: Python :: 3
Classifier: Programming Language :: Python :: 3.11
Classifier: Programming Language :: Python :: 3.12
Classifier: Programming Language :: Python :: 3.13
Classifier: Framework :: AsyncIO
Classifier: Intended Audience :: Developers
Classifier: Intended Audience :: System Administrators
Classifier: Topic :: Home Automation
Requires-Python: >=3.11
License-File: LICENSE
Requires-Dist: aiohttp>=3.9.1
Requires-Dist: yarl>=1.9.4
Dynamic: license-file
